README.md
setup.py
lambda_proxy_cache/__init__.py
lambda_proxy_cache/proxy.py
lambda_proxy_cache.egg-info/PKG-INFO
lambda_proxy_cache.egg-info/SOURCES.txt
lambda_proxy_cache.egg-info/dependency_links.txt
lambda_proxy_cache.egg-info/not-zip-safe
lambda_proxy_cache.egg-info/requires.txt
lambda_proxy_cache.egg-info/top_level.txt
lambda_proxy_cache/backends/__init__.py
lambda_proxy_cache/backends/base.py
lambda_proxy_cache/backends/dynamodb.py
lambda_proxy_cache/backends/memcache.py
lambda_proxy_cache/backends/s3.py