Metadata-Version: 2.1
Name: lambda-proxy-cache
Version: 0.0.1.dev5
Summary: Add cache to lambda-proxy
Home-page: https://github.com/vincentsarago/lambda-proxy-cache
Author: Vincent Sarago
Author-email: vincent.sarago@gmail.com
License: BSD-3
Keywords: AWS-Lambda API-Gateway Request Proxy cache
Platform: UNKNOWN
Classifier: Intended Audience :: Information Technology
Classifier: Intended Audience :: Science/Research
Classifier: License :: OSI Approved :: BSD License
Classifier: Programming Language :: Python :: 3.6
Classifier: Programming Language :: Python :: 3.7
Requires-Python: >=3
Provides-Extra: aws
Provides-Extra: test
Provides-Extra: memcache
Provides-Extra: dev
